airoframework/__init__.py
airoframework/cli.py
airoframework/template/.env
airoframework/template/README.md
airoframework/template/database.db
airoframework/template/main.py
airoframework/template/config/config.py
airoframework/template/config/settings.py
airoframework/template/handlers/handlers.py
airoframework/template/handlers/states.py
airoframework/template/keyboards/keyboards.py
airoframework/template/languages/en.yaml
airoframework/template/languages/uz.yaml
airoframework/template/middlewares/middlewares.py
airoframework/template/requests/request.log
airoframework/template/utils/utils.py
airoframework-1.0.3.dist-info/METADATA
airoframework-1.0.3.dist-info/WHEEL
airoframework-1.0.3.dist-info/entry_points.txt
airoframework-1.0.3.dist-info/top_level.txt
airoframework-1.0.3.dist-info/RECORD
